sambanova/__init__.py
sambanova/_base_client.py
sambanova/_client.py
sambanova/_compat.py
sambanova/_constants.py
sambanova/_exceptions.py
sambanova/_files.py
sambanova/_models.py
sambanova/_qs.py
sambanova/_resource.py
sambanova/_response.py
sambanova/_streaming.py
sambanova/_types.py
sambanova/_version.py
sambanova/py.typed
sambanova/_utils/__init__.py
sambanova/_utils/_compat.py
sambanova/_utils/_datetime_parse.py
sambanova/_utils/_logs.py
sambanova/_utils/_proxy.py
sambanova/_utils/_reflection.py
sambanova/_utils/_resources_proxy.py
sambanova/_utils/_streams.py
sambanova/_utils/_sync.py
sambanova/_utils/_transform.py
sambanova/_utils/_typing.py
sambanova/_utils/_utils.py
sambanova/lib/.keep
sambanova/resources/__init__.py
sambanova/resources/completions.py
sambanova/resources/embeddings.py
sambanova/resources/models.py
sambanova/resources/audio/__init__.py
sambanova/resources/audio/audio.py
sambanova/resources/audio/transcriptions.py
sambanova/resources/audio/translations.py
sambanova/resources/chat/__init__.py
sambanova/resources/chat/chat.py
sambanova/resources/chat/completions.py
sambanova/types/__init__.py
sambanova/types/completion_create_params.py
sambanova/types/completion_create_response.py
sambanova/types/completion_response.py
sambanova/types/completion_stream_response.py
sambanova/types/embedding_create_params.py
sambanova/types/embeddings_response.py
sambanova/types/model_response.py
sambanova/types/models_response.py
sambanova/types/audio/__init__.py
sambanova/types/audio/transcription_create_params.py
sambanova/types/audio/transcription_create_response.py
sambanova/types/audio/transcription_response.py
sambanova/types/audio/transcription_stream_response.py
sambanova/types/audio/translation_create_params.py
sambanova/types/audio/translation_create_response.py
sambanova/types/audio/translation_response.py
sambanova/types/audio/translation_stream_response.py
sambanova/types/chat/__init__.py
sambanova/types/chat/chat_completion_response.py
sambanova-1.3.0.dist-info/METADATA
sambanova-1.3.0.dist-info/WHEEL
sambanova-1.3.0.dist-info/licenses/LICENSE
sambanova-1.3.0.dist-info/RECORD
